odoo/addons/ssi_fixed_asset/README.rst
odoo/addons/ssi_fixed_asset/__init__.py
odoo/addons/ssi_fixed_asset/__manifest__.py
odoo/addons/ssi_fixed_asset/data/account_journal_data.xml
odoo/addons/ssi_fixed_asset/data/approval_template_data.xml
odoo/addons/ssi_fixed_asset/data/ir_sequence_data.xml
odoo/addons/ssi_fixed_asset/data/ir_server_action_data.xml
odoo/addons/ssi_fixed_asset/data/policy_template_data.xml
odoo/addons/ssi_fixed_asset/data/sequence_template_data.xml
odoo/addons/ssi_fixed_asset/i18n/id.po
odoo/addons/ssi_fixed_asset/i18n/ssi_fixed_asset.pot
odoo/addons/ssi_fixed_asset/models/__init__.py
odoo/addons/ssi_fixed_asset/models/account_account.py
odoo/addons/ssi_fixed_asset/models/account_move.py
odoo/addons/ssi_fixed_asset/models/account_move_line.py
odoo/addons/ssi_fixed_asset/models/fixed_asset_asset.py
odoo/addons/ssi_fixed_asset/models/fixed_asset_category.py
odoo/addons/ssi_fixed_asset/models/fixed_asset_depreciation_line.py
odoo/addons/ssi_fixed_asset/models/fixed_asset_depreciation_line_subtype.py
odoo/addons/ssi_fixed_asset/security/account_asset_security.xml
odoo/addons/ssi_fixed_asset/security/ir.model.access.csv
odoo/addons/ssi_fixed_asset/security/ir_module_category_data.xml
odoo/addons/ssi_fixed_asset/security/res_group_data.xml
odoo/addons/ssi_fixed_asset/static/description/banner.png
odoo/addons/ssi_fixed_asset/static/description/icon.png
odoo/addons/ssi_fixed_asset/views/account_account_view.xml
odoo/addons/ssi_fixed_asset/views/account_move_line_views.xml
odoo/addons/ssi_fixed_asset/views/fixed_asset_asset.xml
odoo/addons/ssi_fixed_asset/views/fixed_asset_category.xml
odoo/addons/ssi_fixed_asset/wizards/__init__.py
odoo/addons/ssi_fixed_asset/wizards/mass_depreciation.py
odoo/addons/ssi_fixed_asset/wizards/mass_depreciation_views.xml
odoo14_addon_ssi_fixed_asset-14.0.1.12.0.dist-info/METADATA
odoo14_addon_ssi_fixed_asset-14.0.1.12.0.dist-info/WHEEL
odoo14_addon_ssi_fixed_asset-14.0.1.12.0.dist-info/top_level.txt
odoo14_addon_ssi_fixed_asset-14.0.1.12.0.dist-info/RECORD
